arena/__init__.py
benchmark/__init__.py
benchmark/analyze.py
benchmark/plot.py
benchmark/run.py
benchmark/util.py
benchmark/classic/__init__.py
benchmark/classic/abt_buy.py
benchmark/classic/amazon_google.py
benchmark/classic/beer.py
benchmark/classic/challenging.py
benchmark/classic/dblp_acm.py
benchmark/classic/dblp_scholar.py
benchmark/classic/fodors_zagats.py
benchmark/classic/itunes_amazon.py
benchmark/classic/walmart_amazon.py
benchmark/suite/__init__.py
benchmark/suite/batch.py
benchmark/suite/block.py
benchmark/suite/llama3.py
benchmark/suite/openai.py
benchmark/suite/util.py
cli/__init__.py
cli/libem
libem/__init__.py
libem/constant.py
libem/function.py
libem/interface.py
libem/parameter.py
libem/prompt.py
libem/block/__init__.py
libem/block/function.py
libem/block/interface.py
libem/block/parameter.py
libem/browse/__init__.py
libem/browse/function.py
libem/browse/parameter.py
libem/browse/prompt.py
libem/browse/engines/__init__.py
libem/browse/engines/duckduckgo.py
libem/browse/engines/google.py
libem/compose/__init__.py
libem/compose/function.py
libem/compose/parameter.py
libem/compose/prompt.py
libem/core/__init__.py
libem/core/eval.py
libem/core/exception.py
libem/core/exec.py
libem/core/log.py
libem/core/trace.py
libem/core/util.py
libem/core/model/__init__.py
libem/core/model/claude.py
libem/core/model/llama.py
libem/core/model/openai.py
libem/core/struct/__init__.py
libem/core/struct/parameter.py
libem/core/struct/pattern.py
libem/core/struct/prompt.py
libem/extract/__init__.py
libem/extract/function.py
libem/extract/interface.py
libem/extract/parameter.py
libem/extract/prompt.py
libem/match/__init__.py
libem/match/function.py
libem/match/parameter.py
libem/match/prompt.py
libem/match/interface/__init__.py
libem/match/interface/struct.py
libem/optimize/__init__.py
libem/optimize/function.py
libem/optimize/interface.py
libem/optimize/batch/__init__.py
libem/optimize/batch/provider.py
libem/optimize/cache/__init__.py
libem/optimize/cache/provider.py
libem-0.0.26.dist-info/LICENSE
libem-0.0.26.dist-info/METADATA
libem-0.0.26.dist-info/WHEEL
libem-0.0.26.dist-info/top_level.txt
libem-0.0.26.dist-info/RECORD
