Metadata-Version: 2.1
Name: libem
Version: 0.0.26
Summary: Libem python library
Home-page: UNKNOWN
Author: Systems Design Studio
Author-email: team@SD.studio
License: Apache License, Version 2.0
Platform: UNKNOWN
Requires-Python: >=3.10
License-File: LICENSE
Requires-Dist: pyyaml
Requires-Dist: pytest
Requires-Dist: pydantic
Requires-Dist: openai
Requires-Dist: scikit-learn
Requires-Dist: fuzzywuzzy
Requires-Dist: python-Levenshtein
Requires-Dist: langchain
Requires-Dist: langchain-community
Requires-Dist: langchain-google-community
Requires-Dist: google-api-python-client
Requires-Dist: duckduckgo-search
Requires-Dist: numpy
Requires-Dist: pandas
Requires-Dist: tabulate
Requires-Dist: bs4
Requires-Dist: flask
Requires-Dist: uvicorn
Requires-Dist: requests
Requires-Dist: fastapi
Requires-Dist: tqdm
Requires-Dist: recordlinkage
Requires-Dist: duckdb
Requires-Dist: pymongo
Requires-Dist: anthropic
Requires-Dist: aiolimiter
